[
  {
    "name": "Online Entrepreneurs Cl...",
    "member_count": "182.3K members",
    "image_url": "./groups/ooc.jpg",
    "url": "https://www.facebook.com/groups/oecsl/"
  },

  {
    "name": "pc-builds sL 🇱🇰",
    "member_count": "159.1K members",
    "image_url": "./groups/pcbsl.jpg",
    "url": "https://www.facebook.com/groups/Pcbuildsl/"
  },
  {
    "name": "Fiverr helps Sri Lanka",
    "member_count": "115.8K members",
    "image_url": "./groups/fhs.jpeg",
    "url": "https://www.facebook.com/groups/265732767489820/"
  }
]
